MANIFEST.in
setup.py
capitals/__init__.py
capitals/app.py
capitals.egg-info/PKG-INFO
capitals.egg-info/SOURCES.txt
capitals.egg-info/dependency_links.txt
capitals.egg-info/entry_points.txt
capitals.egg-info/requires.txt
capitals.egg-info/top_level.txt
capitals/data/capitals.txt