Metadata-Version: 1.1
Name: capitals
Version: 0.1.3
Summary: Capitals quiz
Home-page: http://git.km3net.de/jreubelt/capitals.git
Author: Jonas Reubelt
Author-email: UNKNOWN
License: UNKNOWN
Platform: any
Classifier: Development Status :: 3 - Alpha
Classifier: Programming Language :: Python
